<annotation>
	<folder>knife</folder>
	<filename>knife_105.jpg</filename>
	<path>C:\Users\Lenovo\Documents\新建文件夹\knife\knife_105.jpg</path>
	<source>
		<database>Unknown</database>
	</source>
	<size>
		<width>1280</width>
		<height>960</height>
		<depth>3</depth>
	</size>
	<segmented>0</segmented>
	<object>
		<name>knife</name>
		<pose>Unspecified</pose>
		<truncated>0</truncated>
		<difficult>0</difficult>
		<bndbox>
			<xmin>320</xmin>
			<ymin>33</ymin>
			<xmax>986</xmax>
			<ymax>919</ymax>
		</bndbox>
	</object>
</annotation>
