<annotation>
	<folder>phone</folder>
	<filename>phone_175.jpg</filename>
	<path>D:\盲道图片\phone\phone\phone_175.jpg</path>
	<source>
		<database>Unknown</database>
	</source>
	<size>
		<width>490</width>
		<height>367</height>
		<depth>3</depth>
	</size>
	<segmented>0</segmented>
	<object>
		<name>phone</name>
		<pose>Unspecified</pose>
		<truncated>0</truncated>
		<difficult>0</difficult>
		<bndbox>
			<xmin>51</xmin>
			<ymin>41</ymin>
			<xmax>455</xmax>
			<ymax>315</ymax>
		</bndbox>
	</object>
</annotation>
