<annotation>
	<folder>phone</folder>
	<filename>phone_235.jpg</filename>
	<path>D:\盲道图片\phone\phone\phone_235.jpg</path>
	<source>
		<database>Unknown</database>
	</source>
	<size>
		<width>500</width>
		<height>375</height>
		<depth>3</depth>
	</size>
	<segmented>0</segmented>
	<object>
		<name>phone</name>
		<pose>Unspecified</pose>
		<truncated>0</truncated>
		<difficult>0</difficult>
		<bndbox>
			<xmin>227</xmin>
			<ymin>12</ymin>
			<xmax>416</xmax>
			<ymax>365</ymax>
		</bndbox>
	</object>
	<object>
		<name>phone</name>
		<pose>Unspecified</pose>
		<truncated>0</truncated>
		<difficult>0</difficult>
		<bndbox>
			<xmin>89</xmin>
			<ymin>9</ymin>
			<xmax>240</xmax>
			<ymax>368</ymax>
		</bndbox>
	</object>
</annotation>
