<annotation>
	<folder>scissor</folder>
	<filename>scissor_244.jpg</filename>
	<path>C:\Users\HUAWEI\Desktop\scissor\scissor\scissor_244.jpg</path>
	<source>
		<database>Unknown</database>
	</source>
	<size>
		<width>961</width>
		<height>962</height>
		<depth>3</depth>
	</size>
	<segmented>0</segmented>
	<object>
		<name>scissor</name>
		<pose>Unspecified</pose>
		<truncated>0</truncated>
		<difficult>0</difficult>
		<bndbox>
			<xmin>178</xmin>
			<ymin>104</ymin>
			<xmax>915</xmax>
			<ymax>902</ymax>
		</bndbox>
	</object>
</annotation>
